chainmapping/__init__.py
chainmapping/py.typed
chainmapping-0.1.3.dist-info/LICENSE
chainmapping-0.1.3.dist-info/METADATA
chainmapping-0.1.3.dist-info/WHEEL
chainmapping-0.1.3.dist-info/RECORD
